conver/__init__.py
conver/__version__.py
conver/_convert.py
conver/cli.py
conver/conver.py
conver/scripts/convert.jxa
conver/scripts/convert.ps1
conver-0.1.1.dist-info/licenses/LICENSE
conver-0.1.1.dist-info/METADATA
conver-0.1.1.dist-info/WHEEL
conver-0.1.1.dist-info/entry_points.txt
conver-0.1.1.dist-info/top_level.txt
conver-0.1.1.dist-info/RECORD
