Metadata-Version: 2.4
Name: conver
Version: 0.1.1
Summary: A cross-platform Word document converter.
Author-email: Timur Ulyahin <ucomru@pm.me>
License: MIT
Project-URL: Homepage, https://github.com/ucomru/python-conver
Project-URL: Repository, https://github.com/ucomru/python-conver
Project-URL: Documentation, https://github.com/ucomru/python-conver
Project-URL: Issues, https://github.com/ucomru/python-conver/issues
Keywords: conversion,documents,office,tools,cli
Classifier: Programming Language :: Python :: 3
Classifier: Operating System :: MacOS
Classifier: Operating System :: Microsoft :: Windows
Requires-Python: >=3.9
License-File: LICENSE
Requires-Dist: click
Dynamic: license-file
